demoji/__init__.py
demoji/__main__.py
demoji/codes.json
demoji/main.py
demoji-1.1.0.dist-info/LICENSE
demoji-1.1.0.dist-info/METADATA
demoji-1.1.0.dist-info/WHEEL
demoji-1.1.0.dist-info/entry_points.txt
demoji-1.1.0.dist-info/top_level.txt
demoji-1.1.0.dist-info/RECORD
