Metadata-Version: 2.1
Name: demoji
Version: 1.1.0
Summary: Accurately remove and replace emojis in text strings
Home-page: https://github.com/bsolomon1124/demoji
Author: Brad Solomon
Author-email: bsolomon@protonmail.com
License: Apache-2.0
Project-URL: Source, https://github.com/bsolomon1124/demoji
Project-URL: Documentation, https://github.com/bsolomon1124/demoji/blob/master/README.md
Project-URL: Bug Reports, https://github.com/bsolomon1124/demoji/issues
Keywords: emoji,emojis,nlp,natural langauge processing,unicode
Platform: UNKNOWN
Classifier: Development Status :: 3 - Alpha
Classifier: Topic :: Utilities
Classifier: Topic :: Text Processing
Classifier: License :: OSI Approved :: Apache Software License
Classifier: Programming Language :: Python :: 3
Classifier: Programming Language :: Python :: 3 :: Only
Classifier: Programming Language :: Python :: 3.6
Classifier: Programming Language :: Python :: 3.7
Classifier: Programming Language :: Python :: 3.8
Classifier: Programming Language :: Python :: 3.9
Classifier: Programming Language :: Python :: Implementation :: CPython
Requires-Python: >=3.6
Provides-Extra: ujson
License-File: LICENSE
